{
  "schemaVersion": 1,
  "id": "fantastic_worlds",
  "version": "${version}",
  "name": "Fantastic Worlds",
  "description": "A mod all about tweaking your World-Generation. Make your Worlds look more beautiful",
  "accessWidener": "fantastic_worlds.accesswidener",
  "authors": ["RAT Pack Studios"],
  "contact": {},
  "license": "MIT",
  "icon": "assets/fantastic_worlds/icon.png",
  "environment": "*",
  "entrypoints": {
    "fabric-datagen": [
      "mod.rat_pack_studios.fantastic_worlds.client.FantasticWorldsDataGenerator"
    ],
    "client": [
      "mod.rat_pack_studios.fantastic_worlds.client.FantasticWorldsClient"
    ],
    "main": [
      "mod.rat_pack_studios.fantastic_worlds.FantasticWorlds"
    ]
  },
  "mixins": [
    "fantastic_worlds.mixins.json",
    {
      "config": "fantastic_worlds.client.mixins.json",
      "environment": "client"
    }
  ],
  "depends": {
    "fabricloader": ">=0.15.11",
    "fabric": "*",
    "minecraft": ">=1.21"
  }
}
